ephaptic/__init__.py
ephaptic/ephaptic.py
ephaptic/localproxy.py
ephaptic/adapters/__init__.py
ephaptic/adapters/fastapi_.py
ephaptic/adapters/quart_.py
ephaptic/cli/__init__.py
ephaptic/cli/__main__.py
ephaptic/client/__init__.py
ephaptic/client/client.py
ephaptic/transports/__init__.py
ephaptic/transports/fastapi_ws.py
ephaptic/transports/websocket.py
ephaptic-0.2.8.dist-info/licenses/LICENSE
ephaptic-0.2.8.dist-info/METADATA
ephaptic-0.2.8.dist-info/WHEEL
ephaptic-0.2.8.dist-info/entry_points.txt
ephaptic-0.2.8.dist-info/top_level.txt
ephaptic-0.2.8.dist-info/RECORD
