Metadata-Version: 2.4
Name: ephaptic
Version: 0.2.8
Summary: The Python client/server package for ephaptic.
Author-email: uukelele <robustrobot11@gmail.com>
License: MIT License
Project-URL: Homepage, https://github.com/ephaptic/ephaptic
Project-URL: Repository, https://github.com/ephaptic/ephaptic
Project-URL: Issue Tracker, https://github.com/ephaptic/ephaptic/issues
Requires-Python: >=3.10
License-File: LICENSE
Requires-Dist: msgpack>=1.0.0
Requires-Dist: websockets>=12.0
Requires-Dist: pydantic>=2.0
Requires-Dist: typer[standard]>=0.20.0
Requires-Dist: python-dotenv
Requires-Dist: watchfiles
Provides-Extra: server
Requires-Dist: redis; extra == "server"
Dynamic: license-file
